geomt1/__init__.py
geomt1/common.py
geomt1/geomt1.py
geomt1-0.0.1.dist-info/licenses/LICENSE
geomt1-0.0.1.dist-info/METADATA
geomt1-0.0.1.dist-info/WHEEL
geomt1-0.0.1.dist-info/entry_points.txt
geomt1-0.0.1.dist-info/top_level.txt
geomt1-0.0.1.dist-info/RECORD
